stadata_x/__init__.py
stadata_x/api_client.py
stadata_x/app.py
stadata_x/config.py
stadata_x/main.py
stadata_x/assets/app.css
stadata_x/assets/logo.txt
stadata_x/screens/dashboard_screen.py
stadata_x/screens/download_dialog_screen.py
stadata_x/screens/settings_screen.py
stadata_x/screens/table_view_screen.py
stadata_x/screens/welcome_screen.py
stadata_x/widgets/__init__.py
stadata_x/widgets/data_explorer.py
stadata_x/widgets/data_table.py
stadata_x/widgets/footer.py
stadata_x/widgets/header.py
stadata_x/widgets/plot_widget.py
stadata_x/widgets/spinner.py
stadata_x-0.1.7.dist-info/licenses/LICENSE
stadata_x-0.1.7.dist-info/METADATA
stadata_x-0.1.7.dist-info/WHEEL
stadata_x-0.1.7.dist-info/entry_points.txt
stadata_x-0.1.7.dist-info/top_level.txt
stadata_x-0.1.7.dist-info/RECORD
