Metadata-Version: 2.4
Name: stadata-x
Version: 0.1.7
Summary: Terminal UI untuk menjelajahi dan mengunduh data BPS Indonesia secara interaktif
Author-email: Dzakwan Alifi <dzakwan624@gmail.com>
License-Expression: MIT
Project-URL: Homepage, https://github.com/dzakwanalifi/stadata-x
Project-URL: Repository, https://github.com/dzakwanalifi/stadata-x.git
Project-URL: Issues, https://github.com/dzakwanalifi/stadata-x/issues
Project-URL: Documentation, https://github.com/dzakwanalifi/stadata-x#readme
Project-URL: Changelog, https://github.com/dzakwanalifi/stadata-x/blob/main/CHANGELOG.md
Classifier: Development Status :: 4 - Beta
Classifier: Programming Language :: Python :: 3
Classifier: Programming Language :: Python :: 3.9
Classifier: Programming Language :: Python :: 3.10
Classifier: Programming Language :: Python :: 3.11
Classifier: Programming Language :: Python :: 3.12
Classifier: Programming Language :: Python :: 3.13
Classifier: Operating System :: OS Independent
Classifier: Environment :: Console
Classifier: Intended Audience :: Developers
Classifier: Intended Audience :: Science/Research
Classifier: Topic :: Scientific/Engineering :: Information Analysis
Classifier: Topic :: Utilities
Classifier: Natural Language :: Indonesian
Requires-Python: <3.14,>=3.9
License-File: LICENSE
Requires-Dist: stadata
Requires-Dist: textual>=0.50.0
Requires-Dist: plotext>=5.0.0
Requires-Dist: pandas>=1.3.0
Requires-Dist: openpyxl>=3.0.0
Provides-Extra: dev
Requires-Dist: textual-dev; extra == "dev"
Requires-Dist: ruff; extra == "dev"
Dynamic: license-file
